rptk/__init__.py
rptk/__meta__.py
rptk/api.py
rptk/base.py
rptk/command_line.py
rptk/load.py
rptk/rptk.conf.example
rptk/web.py
rptk/format/__init__.py
rptk/format/bird.py
rptk/format/ios.py
rptk/format/ios_null.py
rptk/format/jsonf.py
rptk/format/junos.py
rptk/format/plain.py
rptk/format/yamlf.py
rptk/query/__init__.py
rptk/query/bgpq3.py
rptk/query/native.py
rptk/templates/bird.j2
rptk/templates/ios.j2
rptk/templates/ios_null.j2
rptk/templates/junos.j2
rptk/templates/plain.j2
rptk-0.2.0.dist-info/METADATA
rptk-0.2.0.dist-info/RECORD
rptk-0.2.0.dist-info/WHEEL
rptk-0.2.0.dist-info/entry_points.txt
rptk-0.2.0.dist-info/top_level.txt
