Metadata-Version: 2.1
Name: rptk
Version: 0.2.0
Summary: A python toolkit for prefix filter list management operations.
Home-page: https://github.com/wolcomm/rptk
Author: Workonline Communications
Author-email: communications@workonline.co.za
License: Apache License 2.0
Download-URL: https://github.com/wolcomm/rptk/0.2.0
Platform: UNKNOWN
Classifier: Development Status :: 4 - Beta
Classifier: Intended Audience :: Developers
Classifier: License :: OSI Approved :: Apache Software License
Classifier: Topic :: Software Development :: Libraries :: Python Modules
Classifier: Topic :: Internet
Requires-Dist: Jinja2 (<3.0,>=2.8)
Requires-Dist: PyYAML (<4.0,>=3.11)
Requires-Dist: Flask (<2.0,>=1.0.2)
Requires-Dist: whichcraft (<0.5,>=0.4.1)
Requires-Dist: ipaddress (<2,>=1.0.6); python_version < "3.3"
